aliddns/__init__.py
aliddns/ddns.py
aliddns_python-0.1.2.dist-info/LICENSE
aliddns_python-0.1.2.dist-info/METADATA
aliddns_python-0.1.2.dist-info/WHEEL
aliddns_python-0.1.2.dist-info/top_level.txt
aliddns_python-0.1.2.dist-info/RECORD
