Metadata-Version: 2.1
Name: aliddns-python
Version: 0.1.2
Summary: A Dynamic DNS(DDNS) tool for alicloud
Home-page: https://github.com/cheng10/aliddns-python
Author: cheng10
Author-email: cheng10@ualberta.ca
License: UNKNOWN
Platform: UNKNOWN
Classifier: Programming Language :: Python :: 2
Classifier: Programming Language :: Python :: 3
Classifier: License :: OSI Approved :: MIT License
Classifier: Operating System :: OS Independent
Requires-Dist: docopt
Requires-Dist: requests
Requires-Dist: aliyun-python-sdk-core
Requires-Dist: aliyun-python-sdk-alidns
